pybird/__init__.py
pybird/bird.py
pybird/common.py
pybird/config.py
pybird/correlator.py
pybird/cosmo.py
pybird/emulator.py
pybird/fake.py
pybird/fftlog.py
pybird/fourier.py
pybird/greenfunction.py
pybird/inference.py
pybird/integrated_model_jax.py
pybird/io_pb.py
pybird/jax_special.py
pybird/likelihood.py
pybird/matching.py
pybird/module.py
pybird/nnlo.py
pybird/nonlinear.py
pybird/projection.py
pybird/resum.py
pybird/resumfactor.py
pybird/run.py
pybird/symbolic.py
pybird/symbolic_pofk_linear.py
pybird/utils.py
pybird/emu_data/growth.pkl
pybird/emu_data/growth_model.h5
pybird/emu_data/irps11_80knots_jax_model.h5
pybird/emu_data/irpsct_80knots_jax_model.h5
pybird/emu_data/irpsloop_hex_80knots_jax_model.h5
pybird/emu_data/irpsloop_mono_80knots_jax_model.h5
pybird/emu_data/irpsloop_quad_80knots_jax_model.h5
pybird/emu_data/k_emu.h5
pybird/emu_data/knots.npy
pybird/emu_data/ploopl_hex_80knots_jax_model.h5
pybird/emu_data/ploopl_mono_80knots_jax_model.h5
pybird/emu_data/ploopl_quad_80knots_jax_model.h5
pybird_lss-0.3.2.dist-info/licenses/LICENSE
pybird_lss-0.3.2.dist-info/METADATA
pybird_lss-0.3.2.dist-info/WHEEL
pybird_lss-0.3.2.dist-info/top_level.txt
pybird_lss-0.3.2.dist-info/RECORD
