Metadata-Version: 2.4
Name: pybird-lss
Version: 0.3.2
Summary: EFT predictions for biased tracers in redshift space.
Author: Pierre Zhang, Guido D'Amico and Alexander Reeves
Maintainer: Pierre Zhang, Guido D'Amico, Alexander Reeves
License: The MIT License (MIT)
Project-URL: Home, https://pybird.readthedocs.io
Classifier: Development Status :: 3 - Alpha
Classifier: Intended Audience :: Science/Research
Classifier: License :: OSI Approved :: MIT License
Classifier: Operating System :: OS Independent
Classifier: Environment :: Console
Classifier: Programming Language :: Python :: 3
Classifier: Programming Language :: Python :: 3.8
Classifier: Programming Language :: Python :: 3.9
Classifier: Programming Language :: Python :: 3.10
Classifier: Programming Language :: Python :: 3.11
Requires-Python: >=3.8
License-File: LICENSE
Requires-Dist: numpy>=1.19.0
Requires-Dist: scipy>=1.5.0
Requires-Dist: h5py>=3.0.0
Requires-Dist: pyyaml>=5.0.0
Requires-Dist: emcee>=3.0.0
Requires-Dist: iminuit>=2.0.0
Requires-Dist: platformdirs>=3.0.0
Requires-Dist: fftlog-lss
Requires-Dist: sphinx>=4.0.0
Requires-Dist: sphinx-rtd-theme>=1.0.0
Requires-Dist: nbsphinx>=0.8.0
Requires-Dist: jupyter>=1.0.0
Requires-Dist: ipython>=7.0.0
Requires-Dist: matplotlib>=3.3.0
Requires-Dist: pytest>=6.0.0
Requires-Dist: pytest-cov>=2.0.0
Requires-Dist: black>=21.0.0
Requires-Dist: isort>=5.0.0
Provides-Extra: jax
Requires-Dist: jax>=0.4.0; extra == "jax"
Requires-Dist: jaxlib>=0.4.0; extra == "jax"
Requires-Dist: interpax>=0.2.0; extra == "jax"
Requires-Dist: optax>=0.1.0; extra == "jax"
Requires-Dist: flax>=0.6.0; extra == "jax"
Requires-Dist: numpyro>=0.12.0; extra == "jax"
Requires-Dist: blackjax>=0.9.0; extra == "jax"
Requires-Dist: nautilus-sampler>=0.5.0; extra == "jax"
Dynamic: license-file
